pysidetap/__init__.py
pysidetap/__main__.py
pysidetap/execptions.py
pysidetap/processor.py
pysidetap/libs/__init__.py
pysidetap/libs/operations.py
pysidetap-0.0.10.dist-info/LICENSE
pysidetap-0.0.10.dist-info/METADATA
pysidetap-0.0.10.dist-info/WHEEL
pysidetap-0.0.10.dist-info/entry_points.txt
pysidetap-0.0.10.dist-info/top_level.txt
pysidetap-0.0.10.dist-info/RECORD
