Metadata-Version: 2.1
Name: pysidetap
Version: 0.0.10
Summary: A skeleton template for Python projects.
Home-page: https://github.com/matkapi/pysidetap
Author: Martin Kapinos
Author-email: matkapi19@gmail.com
License: MIT License
Project-URL: webpage, https://github.com/matkapi/pysidetap
Project-URL: Documentation, https://pysidetap.readthedocs.io/en/latest/
Project-URL: Changelog, https://github.com/matkapi/pysidetap/blob/master/CHANGELOG.rst
Project-URL: Issue Tracker, https://github.com/matkapi/pysidetap/issues
Project-URL: Discussion Forum, https://github.com/matkapi/pysidetap/discussions
Keywords: decision-table
Classifier: Development Status :: 4 - Beta
Classifier: License :: OSI Approved :: MIT License
Classifier: Intended Audience :: Science/Research
Classifier: Natural Language :: English
Classifier: Operating System :: POSIX
Classifier: Operating System :: MacOS
Classifier: Operating System :: Microsoft
Classifier: Programming Language :: Python :: 3.10
Classifier: Topic :: Scientific/Engineering :: Bio-Informatics
Requires-Python: >=3.7, <4
License-File: LICENSE
